{"assets/.DS_Store":["assets/.DS_Store"],"assets/Ellipse 329.png":["assets/Ellipse 329.png"],"assets/Group.png":["assets/Group.png"],"assets/Image-1.png":["assets/Image-1.png"],"assets/Image-2.png":["assets/Image-2.png"],"assets/Mobile Image.png":["assets/Mobile Image.png"],"assets/Rectangle 3.png":["assets/Rectangle 3.png"],"assets/Rectangle 4447.png":["assets/Rectangle 4447.png"],"assets/bagrounf_shade.png":["assets/bagrounf_shade.png"],"assets/customer_support.png":["assets/customer_support.png"],"assets/fonts/Gilroy-Black.ttf":["assets/fonts/Gilroy-Black.ttf"],"assets/fonts/Gilroy-Bold.ttf":["assets/fonts/Gilroy-Bold.ttf"],"assets/fonts/Gilroy-ExtraBold.ttf":["assets/fonts/Gilroy-ExtraBold.ttf"],"assets/fonts/Gilroy-Light.ttf":["assets/fonts/Gilroy-Light.ttf"],"assets/fonts/Gilroy-Medium.ttf":["assets/fonts/Gilroy-Medium.ttf"],"assets/fonts/Gilroy-Regular.ttf":["assets/fonts/Gilroy-Regular.ttf"],"assets/fonts/Gilroy-SemiBold.ttf":["assets/fonts/Gilroy-SemiBold.ttf"],"assets/fonts/Gilroy-Thin.ttf":["assets/fonts/Gilroy-Thin.ttf"],"assets/fonts/Inter-Black.ttf":["assets/fonts/Inter-Black.ttf"],"assets/fonts/Inter-Bold.ttf":["assets/fonts/Inter-Bold.ttf"],"assets/fonts/Inter-ExtraBold.ttf":["assets/fonts/Inter-ExtraBold.ttf"],"assets/fonts/Inter-ExtraLight.ttf":["assets/fonts/Inter-ExtraLight.ttf"],"assets/fonts/Inter-Light.ttf":["assets/fonts/Inter-Light.ttf"],"assets/fonts/Inter-Medium.ttf":["assets/fonts/Inter-Medium.ttf"],"assets/fonts/Inter-Regular.ttf":["assets/fonts/Inter-Regular.ttf"],"assets/fonts/Inter-SemiBold.ttf":["assets/fonts/Inter-SemiBold.ttf"],"assets/footer_imsge.png":["assets/footer_imsge.png"],"assets/hero Image group.jpg":["assets/hero Image group.jpg"],"assets/iPhone 15 Pro Black Titanium Mockup Portrait.png":["assets/iPhone 15 Pro Black Titanium Mockup Portrait.png"],"assets/lead_management.png":["assets/lead_management.png"],"assets/leadsofty.png":["assets/leadsofty.png"],"assets/mockup section.png":["assets/mockup section.png"],"assets/security.png":["assets/security.png"],"assets/social_mix.png":["assets/social_mix.png"],"assets/svg/facebook.svg":["assets/svg/facebook.svg"],"assets/svg/linkedin.svg":["assets/svg/linkedin.svg"],"assets/svg/twitter.svg":["assets/svg/twitter.svg"],"assets/team_management.png":["assets/team_management.png"],"packages/cupertino_icons/assets/CupertinoIcons.ttf":["packages/cupertino_icons/assets/CupertinoIcons.ttf"]}